oceana_jwt_auth/__init__.py
oceana_jwt_auth/auth_guard.py
oceana_jwt_auth/auth_provider.py
oceana_jwt_auth/crypto_rsa.py
oceana_jwt_auth/exceptions.py
oceana_jwt_auth/internals.py
oceana_jwt_auth/jwt_extension.py
oceana_jwt_auth/jwt_handler.py
oceana_jwt_auth/api/__init__.py
oceana_jwt_auth/api/common.py
oceana_jwt_auth/auth/__init__.py
oceana_jwt_auth/auth/docs.py
oceana_jwt_auth/auth/models.py
oceana_jwt_auth/config/__init__.py
oceana_jwt_auth/config/config.py
oceana_jwt_auth/database/__init__.py
oceana_jwt_auth/database/auth_repository.py
oceana_jwt_auth/database/db.py
oceana_jwt_auth/models/__init__.py
oceana_jwt_auth/models/db/__init__.py
oceana_jwt_auth/models/db/auth_model.py
oceana_jwt_auth/utils/__init__.py
oceana_jwt_auth/utils/constants.py
oceana_jwt_auth/utils/logger.py
oceana_jwt_auth/utils/utils.py
oceana_jwt_auth-0.0.6.dist-info/METADATA
oceana_jwt_auth-0.0.6.dist-info/WHEEL
oceana_jwt_auth-0.0.6.dist-info/top_level.txt
oceana_jwt_auth-0.0.6.dist-info/RECORD
