Metadata-Version: 2.2
Name: oceana_jwt_auth
Version: 0.0.6
Summary: Oceana API library to manage JWT token in Flask Restx applications
Author: jorgegilramos
License: License :: OSI Approved :: MIT License
Classifier: Programming Language :: Python :: 3
Classifier: License :: OSI Approved :: MIT License
Classifier: Operating System :: OS Independent
Requires-Python: >= 3.9
Requires-Dist: build>=1.2.1
Requires-Dist: setuptools~=67.8.0
Requires-Dist: wheel~=0.38.4
Requires-Dist: requests>=2.29.0
Requires-Dist: python-decouple>=3.8
Requires-Dist: flask==3.1.0
Requires-Dist: flask-restx==1.3.0
Requires-Dist: typing-extensions~=4.12.2
Requires-Dist: pyjwt>=2.8.0
Requires-Dist: SQLAlchemy==2.0.36
Requires-Dist: Flask-SQLAlchemy==3.1.1
Requires-Dist: cryptography>=41.0.7
Requires-Dist: requests-mock>=1.12.1
Requires-Dist: pytest>=7.4.0
Requires-Dist: pytest-env>=1.1.5
Requires-Dist: coverage>=6.4.4
Requires-Dist: flake8>=4.0.1
Provides-Extra: develop
Requires-Dist: requests-mock>=1.12.1; extra == "develop"
Requires-Dist: pytest>=7.4.0; extra == "develop"
Requires-Dist: pytest-env>=1.1.5; extra == "develop"
Requires-Dist: coverage>=6.4.4; extra == "develop"
Requires-Dist: flake8>=4.0.1; extra == "develop"
Requires-Dist: tox==4.23.2; extra == "develop"
Dynamic: author
Dynamic: classifier
Dynamic: description
Dynamic: description-content-type
Dynamic: license
Dynamic: provides-extra
Dynamic: requires-dist
Dynamic: requires-python
Dynamic: summary
